MANIFEST.in
README.txt
setup.cfg
setup.py
docs/HISTORY.txt
docs/INSTALL.txt
docs/LICENSE.GPL
docs/LICENSE.txt
plonetheme/__init__.py
plonetheme.lithium.egg-info/PKG-INFO
plonetheme.lithium.egg-info/SOURCES.txt
plonetheme.lithium.egg-info/dependency_links.txt
plonetheme.lithium.egg-info/entry_points.txt
plonetheme.lithium.egg-info/namespace_packages.txt
plonetheme.lithium.egg-info/not-zip-safe
plonetheme.lithium.egg-info/paster_plugins.txt
plonetheme.lithium.egg-info/requires.txt
plonetheme.lithium.egg-info/top_level.txt
plonetheme/lithium/__init__.py
plonetheme/lithium/configure.zcml
plonetheme/lithium/profiles.zcml
plonetheme/lithium/setuphandlers.py
plonetheme/lithium/skins.zcml
plonetheme/lithium/tests.py
plonetheme/lithium/version.txt
plonetheme/lithium/browser/__init__.py
plonetheme/lithium/browser/__init__.pyo
plonetheme/lithium/browser/configure.zcml
plonetheme/lithium/browser/interfaces.py
plonetheme/lithium/browser/viewlet.pt
plonetheme/lithium/browser/viewlets.py
plonetheme/lithium/browser/images/README.txt
plonetheme/lithium/browser/stylesheets/README.txt
plonetheme/lithium/browser/stylesheets/main.css
plonetheme/lithium/profiles/default/cssregistry.xml
plonetheme/lithium/profiles/default/import_steps.xml
plonetheme/lithium/profiles/default/jsregistry.xml
plonetheme/lithium/profiles/default/metadata.xml
plonetheme/lithium/profiles/default/plonetheme.lithium_various.txt
plonetheme/lithium/profiles/default/skins.xml
plonetheme/lithium/profiles/default/viewlets.xml
plonetheme/lithium/skins/plonetheme_lithium_custom_images/CONTENT.txt
plonetheme/lithium/skins/plonetheme_lithium_custom_images/bg.png
plonetheme/lithium/skins/plonetheme_lithium_custom_images/bullet.png
plonetheme/lithium/skins/plonetheme_lithium_custom_images/calendar.gif
plonetheme/lithium/skins/plonetheme_lithium_custom_images/calendar.png
plonetheme/lithium/skins/plonetheme_lithium_custom_images/category.png
plonetheme/lithium/skins/plonetheme_lithium_custom_images/logo.png
plonetheme/lithium/skins/plonetheme_lithium_custom_images/more.png
plonetheme/lithium/skins/plonetheme_lithium_custom_images/popup_calendar.gif
plonetheme/lithium/skins/plonetheme_lithium_custom_images/post-footer.png
plonetheme/lithium/skins/plonetheme_lithium_custom_images/search-button.png
plonetheme/lithium/skins/plonetheme_lithium_custom_images/user.gif
